xccdfparser/__init__.py
xccdfparser/lib.py
xccdfparser/main.py
xccdfparser/runtests.py
xccdfparser/tests/__init__.py
xccdfparser/tests/test_lib.py
xccdfparser-1.5.1.data/data/LICENSE
xccdfparser-1.5.1.data/data/requirements.txt
xccdfparser-1.5.1.data/data/test-requirements.txt
xccdfparser-1.5.1.data/data/tox.ini
xccdfparser-1.5.1.data/data/test/sample.json
xccdfparser-1.5.1.data/data/test/sample.xml
xccdfparser-1.5.1.dist-info/METADATA
xccdfparser-1.5.1.dist-info/RECORD
xccdfparser-1.5.1.dist-info/WHEEL
xccdfparser-1.5.1.dist-info/entry_points.txt
xccdfparser-1.5.1.dist-info/top_level.txt
