Metadata-Version: 2.1
Name: xccdfparser
Version: 1.5.1
Summary: Parse XCCDF files and produce human-readable outputs
Home-page: UNKNOWN
Author: Vishnuvardhan Kumar
Author-email: vishnukumar1997@gmail.com
License: UNKNOWN
Platform: UNKNOWN
Classifier: Programming Language :: Python :: 2.6
Classifier: Programming Language :: Python :: 2.7
Classifier: Programming Language :: Python :: 3
Classifier: License :: OSI Approved :: MIT License
Classifier: Operating System :: OS Independent
Requires-Dist: lxml
Requires-Dist: IPy
